kasumi/__init__.py
kasumi/abstract.py
kasumi/cls.py
kasumi/embedding.py
kasumi/upload.py
kasumi/utils.py
kasumi_python-0.1.10.dist-info/METADATA
kasumi_python-0.1.10.dist-info/WHEEL
kasumi_python-0.1.10.dist-info/top_level.txt
kasumi_python-0.1.10.dist-info/RECORD
