Metadata-Version: 2.1
Name: kasumi-python
Version: 0.1.10
Summary: Python SDK for kasumi to develop your own app
Home-page: https://github.com/Meduoduo/kasumi-sdk
Author: MIDUODUO LTD.
Author-email: kasumi@miduoduo.org
License: MIT
Classifier: License :: OSI Approved :: MIT License
Classifier: Programming Language :: Python
Classifier: Programming Language :: Python :: 3
Classifier: Programming Language :: Python :: 3.6
Classifier: Programming Language :: Python :: Implementation :: CPython
Classifier: Programming Language :: Python :: Implementation :: PyPy
Requires-Python: >=3.6.0
Requires-Dist: requests
Requires-Dist: flask
Requires-Dist: eventlet
